merge_stardist_masks/__init__.py
merge_stardist_masks/config_2d.py
merge_stardist_masks/data_2d.py
merge_stardist_masks/data_3d.py
merge_stardist_masks/data_base.py
merge_stardist_masks/model_2d.py
merge_stardist_masks/model_3d.py
merge_stardist_masks/mp_worker.py
merge_stardist_masks/naive_fusion.py
merge_stardist_masks/naive_fusion_mp.py
merge_stardist_masks/py.typed
merge_stardist_masks/sample_patches.py
merge_stardist_masks/timeseries_2d.py
merge_stardist_masks/timeseries_helpers.py
merge_stardist_masks/touching_pixels.py
merge_stardist_masks/utils.py
merge_stardist_masks-0.2.4.dist-info/LICENSE.rst
merge_stardist_masks-0.2.4.dist-info/METADATA
merge_stardist_masks-0.2.4.dist-info/WHEEL
merge_stardist_masks-0.2.4.dist-info/RECORD
