Metadata-Version: 2.3
Name: merge-stardist-masks
Version: 0.2.4
Summary: Merge Stardist Masks
License: MIT
Author: Niklas Breitenbach-Netter
Author-email: niknett@gmail.com
Requires-Python: >=3.9.2,<3.13
Classifier: Development Status :: 5 - Production/Stable
Classifier: License :: OSI Approved :: MIT License
Classifier: Programming Language :: Python :: 3
Classifier: Programming Language :: Python :: 3.10
Classifier: Programming Language :: Python :: 3.11
Classifier: Programming Language :: Python :: 3.12
Requires-Dist: cryptography (>=44.0.1)
Requires-Dist: edt (>=2.3,<4.0)
Requires-Dist: loky (>=3.5.5,<4.0.0)
Requires-Dist: numpy (>=1.21.0,<2.0)
Requires-Dist: packaging (>=24.1,<26.0)
Requires-Dist: requests (>=2.31.0)
Requires-Dist: stardist (>=0.7.3,<0.10.0)
Requires-Dist: tqdm (>=4.67.1,<5.0.0)
Project-URL: Changelog, https://github.com/gatoniel/merge-stardist-masks/releases
Project-URL: Documentation, https://merge-stardist-masks.readthedocs.io
Project-URL: Homepage, https://github.com/gatoniel/merge-stardist-masks
Project-URL: Repository, https://github.com/gatoniel/merge-stardist-masks
